tracardi_event_scheduler/plugin.py
tracardi_event_scheduler/model/config.py
tracardi_event_scheduler/model/__pycache__/config.cpython-38.pyc
tracardi_event_scheduler/service/network.py
tracardi_event_scheduler/service/__pycache__/network.cpython-38.pyc
tracardi_event_scheduler/test/test_plugin.py
tracardi_event_scheduler-0.6.0.dist-info/METADATA
tracardi_event_scheduler-0.6.0.dist-info/WHEEL
tracardi_event_scheduler-0.6.0.dist-info/top_level.txt
tracardi_event_scheduler-0.6.0.dist-info/RECORD
