Metadata-Version: 2.1
Name: tracardi-event-scheduler
Version: 0.6.0
Summary: This plugin schedules event at given time.
Home-page: UNKNOWN
Author: Risto Kowaczewski
Author-email: risto.kowaczewski@gmail.com
License: UNKNOWN
Keywords: tracardi,plugin
Platform: UNKNOWN
Classifier: Programming Language :: Python :: 3
Classifier: Operating System :: OS Independent
Requires-Python: >=3.8
Requires-Dist: tracardi-plugin-sdk (>=0.6.18)
Requires-Dist: asyncio
Requires-Dist: tracardi
Requires-Dist: pytimeparse
